LICENSE
README.md
pyproject.toml
setup.py
dameformats/runtests.sh
dameformats.egg-info/PKG-INFO
dameformats.egg-info/SOURCES.txt
dameformats.egg-info/dependency_links.txt
dameformats.egg-info/entry_points.txt
dameformats.egg-info/not-zip-safe
dameformats.egg-info/requires.txt
dameformats.egg-info/top_level.txt
dameformats/files/addresses.csv
dameformats/files/countries.xml
dameformats/files/customers.csv
dameformats/files/david.html
dameformats/files/dump_file.yaml
dameformats/files/example.yaml
dameformats/files/exer1-interface-data.json
dameformats/files/html.html
dameformats/files/items.xml
dameformats/files/min.commas.csv
dameformats/files/min.csv
dameformats/files/partial.csv
dameformats/files/rss.xml
dameformats/files/test.nc
dameformats/src/__init__.py
dameformats/src/dame_formats.py
dameformats/tests/__init__.py
dameformats/tests/test_damecsv.py
dameformats/tests/test_damejson.py
dameformats/tests/test_damenetcdf.py
dameformats/tests/test_damexml.py
dameformats/tests/test_dameyaml.py